basis_poster/Message.py
basis_poster/PlatformHandler.py
basis_poster/__init__.py
basis_poster/functions.py
matrix_sm_poster_basis_poster-0.2.dist-info/COPYING
matrix_sm_poster_basis_poster-0.2.dist-info/LICENSE
matrix_sm_poster_basis_poster-0.2.dist-info/METADATA
matrix_sm_poster_basis_poster-0.2.dist-info/WHEEL
matrix_sm_poster_basis_poster-0.2.dist-info/top_level.txt
matrix_sm_poster_basis_poster-0.2.dist-info/RECORD
