Metadata-Version: 2.1
Name: matrix-sm-poster-basis-poster
Version: 0.2
Summary: The Basis Poster for the matrix-sm-poster.
Author: polyma3000
Classifier: Intended Audience :: Developers
Classifier: License :: OSI Approved :: GNU Lesser General Public License v3 (LGPLv3)
Classifier: Operating System :: OS Independent
Classifier: Programming Language :: Python
Classifier: Programming Language :: Python :: 3
Classifier: Programming Language :: Python :: 3.7
Classifier: Programming Language :: Python :: 3.8
Classifier: Programming Language :: Python :: 3.9
Classifier: Programming Language :: Python :: 3.10
Classifier: Programming Language :: Python :: 3.11
License-File: LICENSE
License-File: COPYING
Requires-Dist: PyYAML
Requires-Dist: apscheduler
